{
  "Id": 2319,
  "Visible": true,
  "Finalized": true,
  "UnlockedDuringEvent": false,
  "CanAttack": true,
  "NameKey": "Frontier Bradley",
  "OasisNameOverride": "",
  "OasisDescOverride": "",
  "Image": "BradleyAdvCard",
  "Frame": "",
  "ManaCost": 3,
  "Damage": "30",
  "Health": "165",
  "HealthLoss": "0",
  "Type": "Character",
  "IngameAssets": [
    "BradleyAdvCharPF",
    "AttackPowerRet",
    "SnakeoilPotionProj",
    "TargetSpellRet"
  ],
  "UIAssets": [
    "BradleyAdvCard"
  ],
  "Targeting": {
    "AssetId": "TargetSpellRet",
    "Radius": 0.0
  },
  "CardUI": "CharCardUI",
  "Tags": [
    "Adv",
    "Character",
    "Epic",
    "Human",
    "Kids",
    "Male",
    "Ranged"
  ],
  "CharacterType": "Ranged",
  "Ingame": "BradleyAdvCharPF",
  "AttackRange": 3.5,
  "TimeToReachMaxVelocity": 0.1,
  "MaxVelocity": 0.8,
  "TimeInBetweenAttacks": 0.5,
  "AgroRangeMultiplier": 3.33,
  "_notes": "",
  "Projectile": {
    "AssetId": "SnakeoilPotionProj",
    "Velocity": 6.0,
    "ProjectileId": "2319_Generic_0",
    "ThrowingAngleDeg": 45
  },
  "PhysicsProperties": {
    "FrictionCoefficient": 1.0,
    "RestingFriction": 0.25,
    "BounceFactor": 0.9,
    "Weight": 30.0
  },
  "KnockbackImpulse": "0.0000",
  "KnockbackAngleDeg": 45.0,
  "ChargedPowerRegen": 0.0,
  "ChargedPowerRadius": 0.0,
  "ChargedPowerReticle": "AttackPowerRet",
  "Rarity": 2,
  "Theme": "Adv",
  "RetreatDistanceFactor": 0.8,
  "RetreatVelocityFactor": 0.3,
  "WalkingAnimationThresholdFactor": 0.2,
  "TargetHeightFactor": 0.8,
  "HealthBarOffset": -0.35,
  "Pows": [
    {
      "Trigger": {
        "Type": "EnteredRadius",
        "Params": {
          "Radius": "100",
          "EnabledByTechTree": false,
          "TriggerDisabled": false
        }
      },
      "UniqueId": "2319_Frontier Bradley_0",
      "Nodes": [
        {
          "Type": "TriggerTargetUnitSelector",
          "Params": {
            "CanSelectAnyUnits": false
          }
        },
        {
          "Type": "FilterFriendsSelector",
          "Params": {
            "CanSelectAnyUnits": false
          }
        },
        {
          "Type": "FilterByTagSelector",
          "Params": {
            "IncludeAll": false,
            "CanSelectAnyUnits": false,
            "Tags": "Melee",
            "ExcludeTags": "AbilityImmune,HasAoeOnTarget,HasAoeOnUnit,Hero"
          }
        },
        {
          "Type": "AOEEffect",
          "Params": {
            "AOEAttackType": "OnTarget",
            "AOERadius": "1.3",
            "AOEDamagePercentage": ".5",
            "AOEAttackConeDegree": "360",
            "AOEKnockbackPercentage": "1",
            "AOETargetVFXAssetId": "BradleyAdvAoEPowerFX"
          },
          "EndTriggers": [
            {
              "Type": "CasterDied"
            },
            {
              "Type": "LeftRadius",
              "Params": {
                "Radius": "100"
              }
            }
          ]
        },
        {
          "Type": "AddTagsEffect",
          "EffectImpact": "Neutral",
          "Params": {
            "Tags": "HasAoeOnTarget",
            "CanSelectAnyUnits": false
          },
          "EndTriggers": [
            {
              "Type": "CasterDied"
            },
            {
              "Type": "LeftRadius",
              "Params": {
                "Radius": "100"
              }
            }
          ]
        },
        {
          "Type": "TriggerTargetUnitSelector",
          "Params": {
            "CanSelectAnyUnits": false
          }
        },
        {
          "Type": "FilterFriendsSelector",
          "Params": {
            "CanSelectAnyUnits": false
          }
        },
        {
          "Type": "FilterByTagSelector",
          "Params": {
            "IncludeAll": false,
            "CanSelectAnyUnits": false,
            "Tags": "Melee",
            "ExcludeTags": "AbilityImmune,AttackchangeImmune,Hero"
          }
        },
        {
          "Type": "VisualEffect",
          "EffectImpact": "Neutral",
          "Params": {
            "AssetId": "GenericBuffLoopPowerFX",
            "IsOffetRelative": false,
            "LockToDefaultDirection": false,
            "BoneName": "Target",
            "OwnerTeamOnly": false,
            "CannotPauseVFX": false,
            "CannotClearVFXOnPause": false,
            "SoundEvent": "PlayAttackBoost",
            "SoundBankName": "SoundBank_FX"
          },
          "EndTriggers": [
            {
              "Type": "CasterDied"
            },
            {
              "Type": "LeftRadius",
              "Params": {
                "Radius": "100"
              }
            }
          ]
        },
        {
          "Type": "AttackBoostEffect",
          "EffectImpact": "Neutral",
          "Params": {
            "Add": "10+PowerAttackBoostAbs",
            "AddVariableId": "PowerAttackBoost",
            "HideIcon": false
          },
          "EndTriggers": [
            {
              "Type": "CasterDied"
            },
            {
              "Type": "LeftRadius",
              "Params": {
                "Radius": "100"
              }
            }
          ]
        }
      ]
    },
    {
      "Trigger": {
        "Type": "Spawned",
        "Params": {
          "EnabledByTechTree": false,
          "EnabledByFSM": false,
          "RemoveAOEVisualWhenPlayed": false,
          "RemoveUnitHighlightWhenPlayed": false
        }
      },
      "UniqueId": "2319_Frontier Bradley_1",
      "Nodes": [
        {
          "Type": "CasterSelector"
        },
        {
          "Type": "VisualEffect",
          "EffectImpact": "Neutral",
          "Params": {
            "AssetId": "BradleyAdvSelfLoopPowerFX",
            "IsOffetRelative": false,
            "LockToDefaultDirection": false,
            "OwnerTeamOnly": false,
            "CannotPauseVFX": false,
            "CannotClearVFXOnPause": false
          }
        }
      ]
    },
    {
      "Trigger": {
        "Type": "ProjectileHit",
        "Params": {
          "ActivateOnSuperPower": false,
          "EnabledByTechTree": false,
          "RemoveAOEVisualWhenPlayed": false,
          "RemoveUnitHighlightWhenPlayed": false
        }
      },
      "UniqueId": "2319_Frontier Bradley_2",
      "Nodes": [
        {
          "Type": "TriggerTargetUnitSelector",
          "Params": {
            "CanSelectAnyUnits": false
          }
        },
        {
          "Type": "VisualEffect",
          "EffectImpact": "Neutral",
          "Params": {
            "AssetId": "BradleyAdvTargetOncePowerFX",
            "IsOffetRelative": false,
            "LockToDefaultDirection": false,
            "BoneName": "Target",
            "OwnerTeamOnly": false,
            "CannotPauseVFX": false,
            "CannotClearVFXOnPause": false
          }
        }
      ]
    }
  ],
  "SameTeamCollisionRadiusMultiplier": 1.0,
  "TechTree2": {
    "Slots": [
      {
        "x": 0,
        "y": 0,
        "type": "TechSlotPropertyModifier",
        "property": "MaxHealth",
        "calculatedValue": 4.89260864,
        "value": 5.0
      },
      {
        "x": 1,
        "y": 0,
        "type": "TechSlotPropertyModifier",
        "property": "Damage",
        "calculatedValue": 1.9799999,
        "value": 2.0
      },
      {
        "x": 2,
        "y": 0,
        "type": "TechSlotPropertyModifier",
        "property": "MaxHealth",
        "calculatedValue": 5.997391,
        "value": 6.0
      },
      {
        "x": 3,
        "y": 0,
        "type": "TechSlotPowerValueModifier",
        "property": "PowerAttackBoostAbs",
        "calculatedValue": 1.65,
        "value": 2.0
      },
      {
        "x": 4,
        "y": 0,
        "type": "TechSlotPropertyModifier",
        "property": "Damage",
        "calculatedValue": 0.831707358,
        "value": 1.0
      },
      {
        "x": 5,
        "y": 0,
        "type": "TechSlotPropertyModifier",
        "property": "MaxHealth",
        "calculatedValue": 6.3525,
        "value": 6.0
      },
      {
        "x": 6,
        "y": 0,
        "type": "TechSlotPropertyModifier",
        "property": "Damage",
        "calculatedValue": 1.01951218,
        "value": 1.0
      },
      {
        "x": 7,
        "y": 0,
        "type": "TechSlotPropertyModifier",
        "property": "MaxHealth",
        "calculatedValue": 7.62299967,
        "value": 8.0
      },
      {
        "x": 8,
        "y": 0,
        "type": "TechSlotPropertyModifier",
        "property": "Damage",
        "calculatedValue": 1.23414636,
        "value": 1.0
      },
      {
        "x": 9,
        "y": 0,
        "type": "TechSlotPowerValueModifier",
        "property": "PowerAttackBoostAbs",
        "calculatedValue": 5.5,
        "value": 6.0
      },
      {
        "x": 10,
        "y": 0,
        "type": "TechSlotPropertyModifier",
        "property": "MaxHealth",
        "calculatedValue": 10.1640005,
        "value": 10.0
      },
      {
        "x": 11,
        "y": 0,
        "type": "TechSlotPropertyModifier",
        "property": "Damage",
        "calculatedValue": 1.63658547,
        "value": 2.0
      },
      {
        "x": 12,
        "y": 0,
        "type": "TechSlotPropertyModifier",
        "property": "MaxHealth",
        "calculatedValue": 12.1605005,
        "value": 12.0
      },
      {
        "x": 13,
        "y": 0,
        "type": "TechSlotPropertyModifier",
        "property": "Damage",
        "calculatedValue": 1.8780489,
        "value": 2.0
      },
      {
        "x": 14,
        "y": 0,
        "type": "TechSlotPropertyModifier",
        "property": "MaxHealth",
        "calculatedValue": 5.891623,
        "value": 6.0
      },
      {
        "x": 15,
        "y": 0,
        "type": "TechSlotPowerValueModifier",
        "property": "PowerAttackBoostAbs",
        "calculatedValue": 2.00520825,
        "value": 2.0
      },
      {
        "x": 16,
        "y": 0,
        "type": "TechSlotPropertyModifier",
        "property": "Damage",
        "calculatedValue": 1.19428563,
        "value": 1.0
      },
      {
        "x": 17,
        "y": 0,
        "type": "TechSlotPropertyModifier",
        "property": "MaxHealth",
        "calculatedValue": 7.982199,
        "value": 8.0
      },
      {
        "x": 18,
        "y": 0,
        "type": "TechSlotPropertyModifier",
        "property": "Damage",
        "calculatedValue": 1.44571424,
        "value": 1.0
      },
      {
        "x": 19,
        "y": 0,
        "type": "TechSlotPropertyModifier",
        "property": "MaxHealth",
        "calculatedValue": 9.69267,
        "value": 10.0
      },
      {
        "x": 20,
        "y": 0,
        "type": "TechSlotPropertyModifier",
        "property": "Damage",
        "calculatedValue": 1.76,
        "value": 2.0
      },
      {
        "x": 21,
        "y": 0,
        "type": "TechSlotPowerValueModifier",
        "property": "PowerAttackBoostAbs",
        "calculatedValue": 3.49479175,
        "value": 3.0
      },
      {
        "x": 22,
        "y": 0,
        "type": "TechSlotPropertyModifier",
        "property": "MaxHealth",
        "calculatedValue": 12.7335081,
        "value": 13.0
      },
      {
        "x": 23,
        "y": 0,
        "type": "TechSlotPropertyModifier",
        "property": "Damage",
        "calculatedValue": 2.2,
        "value": 2.0
      },
      {
        "x": 24,
        "y": 0,
        "type": "TechSlotPropertyModifier",
        "property": "MaxHealth",
        "calculatedValue": 3.5165627,
        "value": 4.0
      },
      {
        "x": 25,
        "y": 0,
        "type": "TechSlotPropertyModifier",
        "property": "Damage",
        "calculatedValue": 0.859801531,
        "value": 1.0
      },
      {
        "x": 26,
        "y": 0,
        "type": "TechSlotPropertyModifier",
        "property": "MaxHealth",
        "calculatedValue": 4.310625,
        "value": 4.0
      },
      {
        "x": 27,
        "y": 0,
        "type": "TechSlotPowerValueModifier",
        "property": "PowerAttackBoostAbs",
        "calculatedValue": 3.09375,
        "value": 3.0
      },
      {
        "x": 28,
        "y": 0,
        "type": "TechSlotPropertyModifier",
        "property": "Damage",
        "calculatedValue": 1.13002491,
        "value": 1.0
      },
      {
        "x": 29,
        "y": 0,
        "type": "TechSlotPropertyModifier",
        "property": "MaxHealth",
        "calculatedValue": 5.78531265,
        "value": 6.0
      },
      {
        "x": 30,
        "y": 0,
        "type": "TechSlotPropertyModifier",
        "property": "Damage",
        "calculatedValue": 1.37568247,
        "value": 1.0
      },
      {
        "x": 31,
        "y": 0,
        "type": "TechSlotPropertyModifier",
        "property": "MaxHealth",
        "calculatedValue": 6.919688,
        "value": 7.0
      },
      {
        "x": 32,
        "y": 0,
        "type": "TechSlotPropertyModifier",
        "property": "Damage",
        "calculatedValue": 1.64590585,
        "value": 2.0
      },
      {
        "x": 33,
        "y": 0,
        "type": "TechSlotPowerValueModifier",
        "property": "PowerAttackBoostAbs",
        "calculatedValue": 5.15625,
        "value": 5.0
      },
      {
        "x": 34,
        "y": 0,
        "type": "TechSlotPropertyModifier",
        "property": "MaxHealth",
        "calculatedValue": 9.075001,
        "value": 9.0
      },
      {
        "x": 35,
        "y": 0,
        "type": "TechSlotPropertyModifier",
        "property": "Damage",
        "calculatedValue": 2.21091819,
        "value": 2.0
      },
      {
        "x": 36,
        "y": 0,
        "type": "TechSlotPropertyModifier",
        "property": "MaxHealth",
        "calculatedValue": 11.2303133,
        "value": 11.0
      },
      {
        "x": 37,
        "y": 0,
        "type": "TechSlotPropertyModifier",
        "property": "Damage",
        "calculatedValue": 2.67766762,
        "value": 3.0
      },
      {
        "x": 38,
        "y": 0,
        "type": "TechSlotPropertyModifier",
        "property": "MaxHealth",
        "calculatedValue": 13.6125,
        "value": 14.0
      },
      {
        "x": 39,
        "y": 0,
        "type": "TechSlotPowerValueModifier",
        "property": "PowerAttackBoostAbs",
        "calculatedValue": 0.6416667,
        "value": 1.0
      },
      {
        "x": 40,
        "y": 0,
        "type": "TechSlotPropertyModifier",
        "property": "Damage",
        "calculatedValue": 0.4210938,
        "value": 1.0
      },
      {
        "x": 41,
        "y": 0,
        "type": "TechSlotPropertyModifier",
        "property": "MaxHealth",
        "calculatedValue": 2.27195287,
        "value": 2.0
      },
      {
        "x": 42,
        "y": 0,
        "type": "TechSlotPropertyModifier",
        "property": "Damage",
        "calculatedValue": 0.5053125,
        "value": 1.0
      },
      {
        "x": 43,
        "y": 0,
        "type": "TechSlotPropertyModifier",
        "property": "MaxHealth",
        "calculatedValue": 2.75025868,
        "value": 3.0
      },
      {
        "x": 44,
        "y": 0,
        "type": "TechSlotPropertyModifier",
        "property": "Damage",
        "calculatedValue": 0.613593757,
        "value": 1.0
      },
      {
        "x": 45,
        "y": 0,
        "type": "TechSlotPowerValueModifier",
        "property": "PowerAttackBoostAbs",
        "calculatedValue": 1.15913987,
        "value": 1.0
      },
      {
        "x": 46,
        "y": 0,
        "type": "TechSlotPropertyModifier",
        "property": "MaxHealth",
        "calculatedValue": 3.64708233,
        "value": 4.0
      },
      {
        "x": 47,
        "y": 0,
        "type": "TechSlotPropertyModifier",
        "property": "Damage",
        "calculatedValue": 0.8060938,
        "value": 1.0
      },
      {
        "x": 48,
        "y": 0,
        "type": "TechSlotPropertyModifier",
        "property": "MaxHealth",
        "calculatedValue": 4.18517637,
        "value": 4.0
      },
      {
        "x": 49,
        "y": 0,
        "type": "TechSlotPropertyModifier",
        "property": "Damage",
        "calculatedValue": 0.962500036,
        "value": 1.0
      },
      {
        "x": 50,
        "y": 0,
        "type": "TechSlotPropertyModifier",
        "property": "MaxHealth",
        "calculatedValue": 5.38094139,
        "value": 5.0
      },
      {
        "x": 51,
        "y": 0,
        "type": "TechSlotPowerValueModifier",
        "property": "PowerAttackBoostAbs",
        "calculatedValue": 2.04919362,
        "value": 2.0
      },
      {
        "x": 52,
        "y": 0,
        "type": "TechSlotPropertyModifier",
        "property": "Damage",
        "calculatedValue": 1.31140637,
        "value": 1.0
      },
      {
        "x": 53,
        "y": 0,
        "type": "TechSlotPropertyModifier",
        "property": "MaxHealth",
        "calculatedValue": 7.17458773,
        "value": 7.0
      },
      {
        "x": 54,
        "y": 0,
        "type": "TechSlotPropertyModifier",
        "property": "Damage",
        "calculatedValue": 0.213125,
        "value": 1.0
      },
      {
        "x": 55,
        "y": 0,
        "type": "TechSlotPropertyModifier",
        "property": "MaxHealth",
        "calculatedValue": 1.57630277,
        "value": 2.0
      },
      {
        "x": 56,
        "y": 0,
        "type": "TechSlotPropertyModifier",
        "property": "Damage",
        "calculatedValue": 0.26125,
        "value": 1.0
      },
      {
        "x": 57,
        "y": 0,
        "type": "TechSlotPowerValueModifier",
        "property": "PowerAttackBoostAbs",
        "calculatedValue": 1.03125,
        "value": 1.0
      },
      {
        "x": 58,
        "y": 0,
        "type": "TechSlotPropertyModifier",
        "property": "MaxHealth",
        "calculatedValue": 2.07171226,
        "value": 2.0
      },
      {
        "x": 59,
        "y": 0,
        "type": "TechSlotPropertyModifier",
        "property": "Damage",
        "calculatedValue": 0.350625,
        "value": 1.0
      },
      {
        "x": 60,
        "y": 0,
        "type": "TechSlotPropertyModifier",
        "property": "MaxHealth",
        "calculatedValue": 2.52208447,
        "value": 3.0
      },
      {
        "x": 61,
        "y": 0,
        "type": "TechSlotPropertyModifier",
        "property": "Damage",
        "calculatedValue": 0.419375032,
        "value": 1.0
      },
      {
        "x": 62,
        "y": 0,
        "type": "TechSlotPropertyModifier",
        "property": "MaxHealth",
        "calculatedValue": 3.017494,
        "value": 3.0
      },
      {
        "x": 63,
        "y": 0,
        "type": "TechSlotPowerValueModifier",
        "property": "PowerAttackBoostAbs",
        "calculatedValue": 1.71875,
        "value": 2.0
      },
      {
        "x": 64,
        "y": 0,
        "type": "TechSlotPropertyModifier",
        "property": "Damage",
        "calculatedValue": 0.55,
        "value": 1.0
      },
      {
        "x": 65,
        "y": 0,
        "type": "TechSlotPropertyModifier",
        "property": "MaxHealth",
        "calculatedValue": 4.05335,
        "value": 4.0
      },
      {
        "x": 66,
        "y": 0,
        "type": "TechSlotPropertyModifier",
        "property": "Damage",
        "calculatedValue": 0.680625,
        "value": 1.0
      },
      {
        "x": 67,
        "y": 0,
        "type": "TechSlotPropertyModifier",
        "property": "MaxHealth",
        "calculatedValue": 4.909057,
        "value": 5.0
      },
      {
        "x": 68,
        "y": 0,
        "type": "TechSlotPropertyModifier",
        "property": "Damage",
        "calculatedValue": 0.825,
        "value": 1.0
      }
    ],
    "Evolve": [
      {
        "StarLevel": 0,
        "Slots": [
          {
            "x": 0,
            "y": 0,
            "type": "TechSlotPropertyModifier",
            "property": "MaxHealth",
            "calculatedValue": 30.25,
            "value": 30.0
          },
          {
            "x": 0,
            "y": 0,
            "type": "TechSlotPropertyModifier",
            "property": "Damage",
            "calculatedValue": 5.50000048,
            "value": 6.0
          }
        ]
      },
      {
        "StarLevel": 1,
        "Slots": [
          {
            "x": 0,
            "y": 0,
            "type": "TechSlotPropertyModifier",
            "property": "MaxHealth",
            "calculatedValue": 90.75,
            "value": 91.0
          },
          {
            "x": 0,
            "y": 0,
            "type": "TechSlotPropertyModifier",
            "property": "Damage",
            "calculatedValue": 16.5000019,
            "value": 17.0
          }
        ]
      },
      {
        "StarLevel": 2,
        "Slots": [
          {
            "x": 0,
            "y": 0,
            "type": "TechSlotPropertyModifier",
            "property": "MaxHealth",
            "calculatedValue": 60.5,
            "value": 60.0
          },
          {
            "x": 0,
            "y": 0,
            "type": "TechSlotPropertyModifier",
            "property": "Damage",
            "calculatedValue": 11.000001,
            "value": 11.0
          }
        ]
      },
      {
        "StarLevel": 3,
        "Slots": [
          {
            "x": 0,
            "y": 0,
            "type": "TechSlotPropertyModifier",
            "property": "MaxHealth",
            "calculatedValue": 30.25,
            "value": 30.0
          },
          {
            "x": 0,
            "y": 0,
            "type": "TechSlotPropertyModifier",
            "property": "Damage",
            "calculatedValue": 5.50000048,
            "value": 6.0
          }
        ]
      },
      {
        "StarLevel": 4,
        "Slots": [
          {
            "x": 0,
            "y": 0,
            "type": "TechSlotPropertyModifier",
            "property": "MaxHealth",
            "calculatedValue": 30.25,
            "value": 30.0
          },
          {
            "x": 0,
            "y": 0,
            "type": "TechSlotPropertyModifier",
            "property": "Damage",
            "calculatedValue": 5.50000048,
            "value": 6.0
          }
        ]
      },
      {
        "StarLevel": 5,
        "Slots": [
          {
            "x": 0,
            "y": 0,
            "type": "TechSlotPropertyModifier",
            "property": "MaxHealth",
            "calculatedValue": 30.25,
            "value": 30.0
          },
          {
            "x": 0,
            "y": 0,
            "type": "TechSlotPropertyModifier",
            "property": "Damage",
            "calculatedValue": 5.50000048,
            "value": 6.0
          }
        ]
      }
    ]
  },
  "Requirements": {
    "MinEpisodeCompleted": 0,
    "MinPlayerLevel": 0,
    "MinPVPRank": 0,
    "MinPVPArena": 9
  },
  "AOEAttackType": "No",
  "AOEDamagePercentage": 0.0,
  "AOERadius": 0.0,
  "AOEAttackConeDegree": 0.0,
  "AOEKnockbackPercentage": 0.0,
  "TargetingType": "Both",
  "PreAttackDelay": 0.0,
  "CanCastOnLava": false,
  "CastArea": "OwnSide",
  "TechtreePatterns": {
    "Upgrades": [
      {
        "PatternType": 0,
        "SlotType": "TechSlotPowerValueModifier",
        "SlotProperty": "PowerAttackBoostAbs",
        "SlotValue": "",
        "MaxMultiplier": "",
        "PowerValue": "10",
        "StartIndex": 4,
        "EndIndex": 0,
        "RepeatInterval": 6,
        "Weighted": true
      }
    ],
    "Evolutions": []
  },
  "OverrideSoundBankName": "",
  "ChildUnitLimit": 0,
  "SpineSkin": "",
  "CastOverrideAnim": "",
  "ColliderRadiusOverride": -1.0,
  "AttackEffect": "",
  "CheckAndRemoveFromDeckOnSpawn": false,
  "ChargedPowerReticlePositionOffset": "",
  "ChargedPowerReticleLockDirection": false
}