{
  "Id": 1517,
  "Visible": false,
  "Finalized": true,
  "UnlockedDuringEvent": false,
  "CanAttack": true,
  "NameKey": "Boss Witch Doctor Token",
  "OasisNameOverride": "",
  "OasisDescOverride": "",
  "Image": "TokenMysCard",
  "Frame": "",
  "ManaCost": 3,
  "Damage": "45",
  "Health": "530",
  "HealthLoss": "0",
  "Type": "Character",
  "IngameAssets": [
    "TokenMysCharPF",
    "AttackPowerRet",
    "TargetSpellRet"
  ],
  "UIAssets": [
    "TokenMysCard"
  ],
  "Targeting": {
    "AssetId": "TargetSpellRet",
    "Radius": 0.0
  },
  "CardUI": "CharCardUI",
  "Tags": [
    "Boss",
    "Character",
    "Enemy",
    "Human",
    "Kids",
    "Legendary",
    "Male",
    "Melee",
    "Mys"
  ],
  "CharacterType": "Melee",
  "Ingame": "TokenMysCharPF",
  "AttackRange": 0.4,
  "TimeToReachMaxVelocity": 0.1,
  "MaxVelocity": 0.675,
  "TimeInBetweenAttacks": 0.5,
  "AgroRangeMultiplier": 5.0,
  "_notes": "Next attack: Damage and leech health off one enemy",
  "PhysicsProperties": {
    "FrictionCoefficient": 1.0,
    "RestingFriction": 0.25,
    "BounceFactor": 0.9,
    "Weight": 30.0
  },
  "KnockbackImpulse": "50.0000",
  "KnockbackAngleDeg": 45.0,
  "ChargedPowerRegen": 0.1,
  "ChargedPowerRadius": 1.0,
  "ChargedPowerReticle": "AttackPowerRet",
  "Rarity": 3,
  "Theme": "Mys",
  "RetreatDistanceFactor": 0.8,
  "RetreatVelocityFactor": 0.3,
  "WalkingAnimationThresholdFactor": 0.2,
  "TargetHeightFactor": 0.8,
  "HealthBarOffset": -0.35,
  "Pows": [
    {
      "Trigger": {
        "Type": "ChargedPowerActivated",
        "Params": {
          "Automatic": false,
          "Delay": "0.6",
          "EnabledByTechTree": false,
          "EnabledByFSM": false
        }
      },
      "UniqueId": "1517_DrainAndHeal",
      "Nodes": [
        {
          "Type": "CasterSelector"
        },
        {
          "Type": "CreateNamedValueEffect",
          "EffectImpact": "Neutral",
          "Params": {
            "Name": "StoredTokenMysHealthValue",
            "Value": "GetProperty(CasterId,'MaxHealth')",
            "Required": false
          }
        },
        {
          "Type": "NearestUnitsSelector",
          "Params": {
            "CanSelectAnyUnits": false,
            "MaximumDistance": "1.5",
            "Side": "Enemy",
            "ExcludeTags": "Boss,HealImmune,MovingObject,Object",
            "IncludeCaster": false
          }
        },
        {
          "Type": "DamageEffect",
          "Params": {
            "Amount": "(StoredTokenMysHealthValue/2)+PowerStealHPAbs",
            "AmountVariableId": "PowerStealAmount",
            "SimpleAmount": "GetProperty(CasterId,'Health')/2+PowerStealHPAbs",
            "HideDamage": false
          }
        },
        {
          "Type": "VisualEffect",
          "EffectImpact": "Neutral",
          "Params": {
            "AssetId": "VoodooSpellOncePowerFX",
            "BoneName": "Target",
            "OwnerTeamOnly": false
          }
        },
        {
          "Type": "FocusEffect",
          "Params": {
            "OnStart": true
          }
        },
        {
          "Type": "IfSelectionCountIsGreaterThanConditionEffect",
          "Params": {
            "Amount": "0"
          }
        },
        {
          "Type": "CasterSelector"
        },
        {
          "Type": "HealEffect",
          "Params": {
            "Amount": "StoredTokenMysHealthValue/2+PowerStealHPAbs"
          }
        },
        {
          "Type": "IfEndConditionEffect"
        }
      ]
    },
    {
      "Trigger": {
        "Type": "AnimationStarted",
        "Params": {
          "AnimationName": "SuperPower",
          "EnabledByTechTree": false
        }
      },
      "UniqueId": "1517_GlowVFX",
      "Nodes": [
        {
          "Type": "CasterSelector"
        },
        {
          "Type": "VisualEffect",
          "EffectImpact": "Neutral",
          "Params": {
            "AssetId": "VoodooGlowOncePowerFX",
            "OwnerTeamOnly": false
          }
        },
        {
          "Type": "NearestUnitsSelector",
          "Params": {
            "CanSelectAnyUnits": false,
            "MaximumDistance": "1.5",
            "Side": "Enemy",
            "ExcludeTags": "Boss,HealImmune,MovingObject,Object",
            "IncludeCaster": false
          }
        },
        {
          "Type": "SoundEffect",
          "EffectImpact": "Neutral",
          "Params": {
            "SoundEvent": "PlayTokenMysSuperHit",
            "SoundBankName": "SoundBank_TokenMys"
          }
        }
      ]
    }
  ],
  "SameTeamCollisionRadiusMultiplier": 1.0,
  "TechTree2": {
    "Slots": [
      {
        "x": 0,
        "y": 0,
        "type": "TechSlotPropertyModifier",
        "property": "MaxHealth",
        "calculatedValue": 21.7161751,
        "value": 22.0
      },
      {
        "x": 1,
        "y": 0,
        "type": "TechSlotPropertyModifier",
        "property": "Damage",
        "calculatedValue": 1.86545467,
        "value": 2.0
      },
      {
        "x": 2,
        "y": 0,
        "type": "TechSlotPropertyModifier",
        "property": "MaxHealth",
        "calculatedValue": 26.6198273,
        "value": 27.0
      },
      {
        "x": 3,
        "y": 0,
        "type": "TechSlotPropertyModifier",
        "property": "Damage",
        "calculatedValue": 2.23854566,
        "value": 2.0
      },
      {
        "x": 4,
        "y": 0,
        "type": "TechSlotPropertyModifier",
        "property": "MaxHealth",
        "calculatedValue": 14.6903524,
        "value": 15.0
      },
      {
        "x": 5,
        "y": 0,
        "type": "TechSlotPropertyModifier",
        "property": "Damage",
        "calculatedValue": 1.29405415,
        "value": 1.0
      },
      {
        "x": 6,
        "y": 0,
        "type": "TechSlotPropertyModifier",
        "property": "MaxHealth",
        "calculatedValue": 18.0075283,
        "value": 18.0
      },
      {
        "x": 7,
        "y": 0,
        "type": "TechSlotPropertyModifier",
        "property": "Damage",
        "calculatedValue": 1.552865,
        "value": 2.0
      },
      {
        "x": 8,
        "y": 0,
        "type": "TechSlotPropertyModifier",
        "property": "MaxHealth",
        "calculatedValue": 21.7985878,
        "value": 22.0
      },
      {
        "x": 9,
        "y": 0,
        "type": "TechSlotPropertyModifier",
        "property": "Damage",
        "calculatedValue": 1.88562179,
        "value": 2.0
      },
      {
        "x": 10,
        "y": 0,
        "type": "TechSlotPropertyModifier",
        "property": "MaxHealth",
        "calculatedValue": 26.5374126,
        "value": 27.0
      },
      {
        "x": 11,
        "y": 0,
        "type": "TechSlotPropertyModifier",
        "property": "Damage",
        "calculatedValue": 2.25535154,
        "value": 2.0
      },
      {
        "x": 12,
        "y": 0,
        "type": "TechSlotPropertyModifier",
        "property": "MaxHealth",
        "calculatedValue": 31.7501183,
        "value": 32.0
      },
      {
        "x": 13,
        "y": 0,
        "type": "TechSlotPropertyModifier",
        "property": "Damage",
        "calculatedValue": 2.5881083,
        "value": 3.0
      },
      {
        "x": 14,
        "y": 0,
        "type": "TechSlotPropertyModifier",
        "property": "MaxHealth",
        "calculatedValue": 14.6903524,
        "value": 15.0
      },
      {
        "x": 15,
        "y": 0,
        "type": "TechSlotPropertyModifier",
        "property": "Damage",
        "calculatedValue": 1.29405415,
        "value": 1.0
      },
      {
        "x": 16,
        "y": 0,
        "type": "TechSlotPropertyModifier",
        "property": "MaxHealth",
        "calculatedValue": 18.0075283,
        "value": 18.0
      },
      {
        "x": 17,
        "y": 0,
        "type": "TechSlotPropertyModifier",
        "property": "Damage",
        "calculatedValue": 1.552865,
        "value": 2.0
      },
      {
        "x": 18,
        "y": 0,
        "type": "TechSlotPropertyModifier",
        "property": "MaxHealth",
        "calculatedValue": 21.7985878,
        "value": 22.0
      },
      {
        "x": 19,
        "y": 0,
        "type": "TechSlotPropertyModifier",
        "property": "Damage",
        "calculatedValue": 1.88562179,
        "value": 2.0
      },
      {
        "x": 20,
        "y": 0,
        "type": "TechSlotPropertyModifier",
        "property": "MaxHealth",
        "calculatedValue": 26.5374126,
        "value": 27.0
      },
      {
        "x": 21,
        "y": 0,
        "type": "TechSlotPropertyModifier",
        "property": "Damage",
        "calculatedValue": 2.25535154,
        "value": 2.0
      },
      {
        "x": 22,
        "y": 0,
        "type": "TechSlotPropertyModifier",
        "property": "MaxHealth",
        "calculatedValue": 31.7501183,
        "value": 32.0
      },
      {
        "x": 23,
        "y": 0,
        "type": "TechSlotPropertyModifier",
        "property": "Damage",
        "calculatedValue": 2.5881083,
        "value": 3.0
      },
      {
        "x": 24,
        "y": 0,
        "type": "TechSlotPropertyModifier",
        "property": "MaxHealth",
        "calculatedValue": 10.2312708,
        "value": 10.0
      },
      {
        "x": 25,
        "y": 0,
        "type": "TechSlotPropertyModifier",
        "property": "Damage",
        "calculatedValue": 1.14995646,
        "value": 1.0
      },
      {
        "x": 26,
        "y": 0,
        "type": "TechSlotPropertyModifier",
        "property": "MaxHealth",
        "calculatedValue": 12.5415573,
        "value": 13.0
      },
      {
        "x": 27,
        "y": 0,
        "type": "TechSlotPropertyModifier",
        "property": "Damage",
        "calculatedValue": 1.37994778,
        "value": 1.0
      },
      {
        "x": 28,
        "y": 0,
        "type": "TechSlotPropertyModifier",
        "property": "MaxHealth",
        "calculatedValue": 15.1818857,
        "value": 15.0
      },
      {
        "x": 29,
        "y": 0,
        "type": "TechSlotPropertyModifier",
        "property": "Damage",
        "calculatedValue": 1.67565084,
        "value": 2.0
      },
      {
        "x": 30,
        "y": 0,
        "type": "TechSlotPropertyModifier",
        "property": "MaxHealth",
        "calculatedValue": 18.482296,
        "value": 18.0
      },
      {
        "x": 31,
        "y": 0,
        "type": "TechSlotPropertyModifier",
        "property": "Damage",
        "calculatedValue": 2.00421,
        "value": 2.0
      },
      {
        "x": 32,
        "y": 0,
        "type": "TechSlotPropertyModifier",
        "property": "MaxHealth",
        "calculatedValue": 22.1127472,
        "value": 22.0
      },
      {
        "x": 33,
        "y": 0,
        "type": "TechSlotPropertyModifier",
        "property": "Damage",
        "calculatedValue": 2.299913,
        "value": 2.0
      },
      {
        "x": 34,
        "y": 0,
        "type": "TechSlotPropertyModifier",
        "property": "MaxHealth",
        "calculatedValue": 26.4032784,
        "value": 26.0
      },
      {
        "x": 35,
        "y": 0,
        "type": "TechSlotPropertyModifier",
        "property": "Damage",
        "calculatedValue": 2.957031,
        "value": 3.0
      },
      {
        "x": 36,
        "y": 0,
        "type": "TechSlotPropertyModifier",
        "property": "MaxHealth",
        "calculatedValue": 32.674057,
        "value": 33.0
      },
      {
        "x": 37,
        "y": 0,
        "type": "TechSlotPropertyModifier",
        "property": "Damage",
        "calculatedValue": 3.581293,
        "value": 4.0
      },
      {
        "x": 38,
        "y": 0,
        "type": "TechSlotPropertyModifier",
        "property": "MaxHealth",
        "calculatedValue": 39.6049156,
        "value": 40.0
      },
      {
        "x": 39,
        "y": 0,
        "type": "TechSlotPropertyModifier",
        "property": "Damage",
        "calculatedValue": 0.8686929,
        "value": 1.0
      },
      {
        "x": 40,
        "y": 0,
        "type": "TechSlotPropertyModifier",
        "property": "MaxHealth",
        "calculatedValue": 13.543931,
        "value": 14.0
      },
      {
        "x": 41,
        "y": 0,
        "type": "TechSlotPropertyModifier",
        "property": "Damage",
        "calculatedValue": 1.06484926,
        "value": 1.0
      },
      {
        "x": 42,
        "y": 0,
        "type": "TechSlotPropertyModifier",
        "property": "MaxHealth",
        "calculatedValue": 16.2527161,
        "value": 16.0
      },
      {
        "x": 43,
        "y": 0,
        "type": "TechSlotPropertyModifier",
        "property": "Damage",
        "calculatedValue": 1.28902817,
        "value": 1.0
      },
      {
        "x": 44,
        "y": 0,
        "type": "TechSlotPropertyModifier",
        "property": "MaxHealth",
        "calculatedValue": 19.7354412,
        "value": 20.0
      },
      {
        "x": 45,
        "y": 0,
        "type": "TechSlotPropertyModifier",
        "property": "Damage",
        "calculatedValue": 1.56925166,
        "value": 2.0
      },
      {
        "x": 46,
        "y": 0,
        "type": "TechSlotPropertyModifier",
        "property": "MaxHealth",
        "calculatedValue": 23.6051369,
        "value": 24.0
      },
      {
        "x": 47,
        "y": 0,
        "type": "TechSlotPropertyModifier",
        "property": "Damage",
        "calculatedValue": 1.87749755,
        "value": 2.0
      },
      {
        "x": 48,
        "y": 0,
        "type": "TechSlotPropertyModifier",
        "property": "MaxHealth",
        "calculatedValue": 27.087862,
        "value": 27.0
      },
      {
        "x": 49,
        "y": 0,
        "type": "TechSlotPropertyModifier",
        "property": "Damage",
        "calculatedValue": 2.241788,
        "value": 2.0
      },
      {
        "x": 50,
        "y": 0,
        "type": "TechSlotPropertyModifier",
        "property": "MaxHealth",
        "calculatedValue": 34.82725,
        "value": 35.0
      },
      {
        "x": 51,
        "y": 0,
        "type": "TechSlotPropertyModifier",
        "property": "Damage",
        "calculatedValue": 2.7742126,
        "value": 3.0
      },
      {
        "x": 52,
        "y": 0,
        "type": "TechSlotPropertyModifier",
        "property": "MaxHealth",
        "calculatedValue": 42.17967,
        "value": 42.0
      },
      {
        "x": 53,
        "y": 0,
        "type": "TechSlotPropertyModifier",
        "property": "Damage",
        "calculatedValue": 3.36268187,
        "value": 3.0
      },
      {
        "x": 54,
        "y": 0,
        "type": "TechSlotPropertyModifier",
        "property": "MaxHealth",
        "calculatedValue": 10.2312708,
        "value": 10.0
      },
      {
        "x": 55,
        "y": 0,
        "type": "TechSlotPropertyModifier",
        "property": "Damage",
        "calculatedValue": 1.14995646,
        "value": 1.0
      },
      {
        "x": 56,
        "y": 0,
        "type": "TechSlotPropertyModifier",
        "property": "MaxHealth",
        "calculatedValue": 12.5415573,
        "value": 13.0
      },
      {
        "x": 57,
        "y": 0,
        "type": "TechSlotPropertyModifier",
        "property": "Damage",
        "calculatedValue": 1.37994778,
        "value": 1.0
      },
      {
        "x": 58,
        "y": 0,
        "type": "TechSlotPropertyModifier",
        "property": "MaxHealth",
        "calculatedValue": 15.1818857,
        "value": 15.0
      },
      {
        "x": 59,
        "y": 0,
        "type": "TechSlotPropertyModifier",
        "property": "Damage",
        "calculatedValue": 1.67565084,
        "value": 2.0
      },
      {
        "x": 60,
        "y": 0,
        "type": "TechSlotPropertyModifier",
        "property": "MaxHealth",
        "calculatedValue": 18.482296,
        "value": 18.0
      },
      {
        "x": 61,
        "y": 0,
        "type": "TechSlotPropertyModifier",
        "property": "Damage",
        "calculatedValue": 2.00421,
        "value": 2.0
      },
      {
        "x": 62,
        "y": 0,
        "type": "TechSlotPropertyModifier",
        "property": "MaxHealth",
        "calculatedValue": 22.1127472,
        "value": 22.0
      },
      {
        "x": 63,
        "y": 0,
        "type": "TechSlotPropertyModifier",
        "property": "Damage",
        "calculatedValue": 2.299913,
        "value": 2.0
      },
      {
        "x": 64,
        "y": 0,
        "type": "TechSlotPropertyModifier",
        "property": "MaxHealth",
        "calculatedValue": 26.4032784,
        "value": 26.0
      },
      {
        "x": 65,
        "y": 0,
        "type": "TechSlotPropertyModifier",
        "property": "Damage",
        "calculatedValue": 2.957031,
        "value": 3.0
      },
      {
        "x": 66,
        "y": 0,
        "type": "TechSlotPropertyModifier",
        "property": "MaxHealth",
        "calculatedValue": 32.674057,
        "value": 33.0
      },
      {
        "x": 67,
        "y": 0,
        "type": "TechSlotPropertyModifier",
        "property": "Damage",
        "calculatedValue": 3.581293,
        "value": 4.0
      },
      {
        "x": 68,
        "y": 0,
        "type": "TechSlotPropertyModifier",
        "property": "MaxHealth",
        "calculatedValue": 39.6049156,
        "value": 40.0
      }
    ],
    "Evolve": [
      {
        "StarLevel": 0,
        "Slots": [
          {
            "x": 0,
            "y": 0,
            "type": "TechSlotPropertyModifier",
            "property": "MaxHealth",
            "calculatedValue": 75.525,
            "value": 76.0
          },
          {
            "x": 0,
            "y": 0,
            "type": "TechSlotPropertyModifier",
            "property": "Damage",
            "calculatedValue": 6.412501,
            "value": 6.0
          }
        ]
      },
      {
        "StarLevel": 1,
        "Slots": [
          {
            "x": 0,
            "y": 0,
            "type": "TechSlotPropertyModifier",
            "property": "MaxHealth",
            "calculatedValue": 113.287506,
            "value": 113.0
          },
          {
            "x": 0,
            "y": 0,
            "type": "TechSlotPropertyModifier",
            "property": "Damage",
            "calculatedValue": 9.618752,
            "value": 10.0
          }
        ]
      },
      {
        "StarLevel": 2,
        "Slots": [
          {
            "x": 0,
            "y": 0,
            "type": "TechSlotPropertyModifier",
            "property": "MaxHealth",
            "calculatedValue": 151.05,
            "value": 151.0
          },
          {
            "x": 0,
            "y": 0,
            "type": "TechSlotPropertyModifier",
            "property": "Damage",
            "calculatedValue": 12.8250017,
            "value": 13.0
          }
        ]
      },
      {
        "StarLevel": 3,
        "Slots": [
          {
            "x": 0,
            "y": 0,
            "type": "TechSlotPropertyModifier",
            "property": "MaxHealth",
            "calculatedValue": 188.8125,
            "value": 189.0
          },
          {
            "x": 0,
            "y": 0,
            "type": "TechSlotPropertyModifier",
            "property": "Damage",
            "calculatedValue": 16.0312519,
            "value": 16.0
          }
        ]
      },
      {
        "StarLevel": 4,
        "Slots": [
          {
            "x": 0,
            "y": 0,
            "type": "TechSlotPropertyModifier",
            "property": "MaxHealth",
            "calculatedValue": 302.1,
            "value": 302.0
          },
          {
            "x": 0,
            "y": 0,
            "type": "TechSlotPropertyModifier",
            "property": "Damage",
            "calculatedValue": 25.6500034,
            "value": 26.0
          }
        ]
      },
      {
        "StarLevel": 5,
        "Slots": [
          {
            "x": 0,
            "y": 0,
            "type": "TechSlotPropertyModifier",
            "property": "MaxHealth",
            "calculatedValue": 377.625,
            "value": 378.0
          },
          {
            "x": 0,
            "y": 0,
            "type": "TechSlotPropertyModifier",
            "property": "Damage",
            "calculatedValue": 32.0625038,
            "value": 32.0
          }
        ]
      }
    ]
  },
  "Requirements": {
    "MinEpisodeCompleted": 3,
    "MinPlayerLevel": 0,
    "MinPVPRank": 0,
    "MinPVPArena": 0
  },
  "AOEAttackType": "No",
  "AOEDamagePercentage": 0.0,
  "AOERadius": 0.0,
  "AOEKnockbackPercentage": 0.0,
  "TargetingType": "Ground",
  "PreAttackDelay": 0.0,
  "CanCastOnLava": false,
  "CastArea": "OwnSide",
  "TechtreePatterns": {
    "Upgrades": [],
    "Evolutions": []
  },
  "OverrideSoundBankName": "",
  "ChildUnitLimit": 0,
  "SpineSkin": "",
  "ColliderRadiusOverride": -1.0,
  "CheckAndRemoveFromDeckOnSpawn": false
}