{
  "Id": 38,
  "Visible": true,
  "Finalized": true,
  "UnlockedDuringEvent": false,
  "CanAttack": true,
  "NameKey": "Awesomo 4000",
  "OasisNameOverride": "",
  "OasisDescOverride": "",
  "Image": "CartmanSciCard",
  "Frame": "",
  "ManaCost": 5,
  "Damage": "21",
  "Health": "684",
  "HealthLoss": "0",
  "Type": "Character",
  "IngameAssets": [
    "CartmanSciCharPF",
    "FreezePowerRet",
    "TargetSpellRet"
  ],
  "UIAssets": [
    "CartmanSciCard"
  ],
  "Targeting": {
    "AssetId": "TargetSpellRet",
    "Radius": 0.0
  },
  "CardUI": "CharCardUI",
  "Tags": [
    "Character",
    "Epic",
    "Human",
    "Kids",
    "Male",
    "Sci",
    "Tank"
  ],
  "CharacterType": "Tank",
  "Ingame": "CartmanSciCharPF",
  "AttackRange": 1.05,
  "TimeToReachMaxVelocity": 0.1,
  "MaxVelocity": 0.27,
  "TimeInBetweenAttacks": 0.5,
  "AgroRangeMultiplier": 4.76,
  "_notes": "",
  "PhysicsProperties": {
    "FrictionCoefficient": 1.0,
    "RestingFriction": 0.25,
    "BounceFactor": 0.9,
    "Weight": 70.0
  },
  "KnockbackImpulse": "40.0000",
  "KnockbackAngleDeg": 45.0,
  "ChargedPowerRegen": 0.06666667,
  "ChargedPowerRadius": 2.0,
  "ChargedPowerReticle": "FreezePowerRet",
  "Rarity": 2,
  "Theme": "Sci",
  "RetreatDistanceFactor": 0.8,
  "RetreatVelocityFactor": 0.3,
  "WalkingAnimationThresholdFactor": 0.2,
  "TargetHeightFactor": 0.8,
  "HealthBarOffset": -0.35,
  "Pows": [
    {
      "Trigger": {
        "Type": "ChargedPowerActivated",
        "Params": {
          "Automatic": false,
          "Delay": "0.25",
          "EnabledByTechTree": false,
          "EnabledByFSM": false,
          "SimulateSelectionDuringAnimation": false
        }
      },
      "UniqueId": "TerminatorCartmanPowers",
      "Nodes": [
        {
          "Type": "CasterSelector"
        },
        {
          "Type": "NearestUnitsSelector",
          "Params": {
            "CanSelectAnyUnits": false,
            "MaximumDistance": "2+PowerRangeAbs",
            "MaximumDistanceVariableId": "PowerRange",
            "Side": "Enemy",
            "ExcludeTags": "FreezeImmune,Object",
            "IncludeCaster": false,
            "CanSelectTraps": false
          }
        },
        {
          "Type": "FreezeEffect",
          "EffectImpact": "Negative",
          "Params": {
            "MuteFreezeSound": false,
            "CannotDeactivateEarly": false,
            "RemoveAllFreezeEffects": false
          },
          "EndTriggers": [
            {
              "Type": "ElapsedTimeSinceActivation",
              "Params": {
                "ElapsedTime": "4.0",
                "ElapsedTimeVariableId": "PowerDuration"
              }
            }
          ]
        },
        {
          "Type": "VisualEffect",
          "EffectImpact": "Neutral",
          "Params": {
            "AssetId": "CartmanSci_IcePillarPowerFX",
            "OwnerTeamOnly": false,
            "CannotPauseVFX": false,
            "CannotClearVFXOnPause": false,
            "SoundEvent": "PlayCartmanSciSuperpowerLoop",
            "SoundEventOnDestroy": "StopCartmanSciSuperpowerLoop",
            "SoundBankName": "SoundBank_CartmanSci"
          },
          "EndTriggers": [
            {
              "Type": "ElapsedTimeSinceActivation",
              "Params": {
                "ElapsedTime": "4.0"
              }
            }
          ]
        },
        {
          "Type": "SoundEffect",
          "EffectImpact": "Neutral",
          "Params": {
            "SoundEvent": "PlayFreezePower",
            "SoundBankName": "SoundBank_FX"
          }
        }
      ]
    },
    {
      "Trigger": {
        "Type": "AnimationStarted",
        "Params": {
          "AnimationName": "SuperPower",
          "EnabledByTechTree": false
        }
      },
      "UniqueId": "Awesomo4000SuperPowerVFX",
      "Nodes": [
        {
          "Type": "CasterSelector"
        },
        {
          "Type": "VisualEffect",
          "EffectImpact": "Neutral",
          "Params": {
            "AssetId": "CartmanSciOncePowerFX",
            "Scale": "2+PowerRangeAbs",
            "OwnerTeamOnly": false,
            "CannotPauseVFX": false,
            "CannotClearVFXOnPause": false
          },
          "EndTriggers": [
            {
              "Type": "ElapsedTimeSinceActivation",
              "Params": {
                "ElapsedTime": "5.0"
              }
            }
          ]
        }
      ]
    }
  ],
  "SameTeamCollisionRadiusMultiplier": 1.0,
  "TechTree2": {
    "Slots": [
      {
        "x": 0,
        "y": 0,
        "type": "TechSlotPropertyModifier",
        "property": "MaxHealth",
        "calculatedValue": 20.28209,
        "value": 20.0
      },
      {
        "x": 1,
        "y": 0,
        "type": "TechSlotPropertyModifier",
        "property": "Damage",
        "calculatedValue": 1.38599992,
        "value": 1.0
      },
      {
        "x": 2,
        "y": 0,
        "type": "TechSlotPropertyModifier",
        "property": "MaxHealth",
        "calculatedValue": 24.8619137,
        "value": 25.0
      },
      {
        "x": 3,
        "y": 0,
        "type": "TechSlotPowerValueModifier",
        "property": "PowerRangeAbs",
        "calculatedValue": 0.125,
        "value": 0.12
      },
      {
        "x": 4,
        "y": 0,
        "type": "TechSlotPropertyModifier",
        "property": "Damage",
        "calculatedValue": 0.5942739,
        "value": 1.0
      },
      {
        "x": 5,
        "y": 0,
        "type": "TechSlotPropertyModifier",
        "property": "MaxHealth",
        "calculatedValue": 27.8666668,
        "value": 28.0
      },
      {
        "x": 6,
        "y": 0,
        "type": "TechSlotPropertyModifier",
        "property": "Damage",
        "calculatedValue": 0.7284648,
        "value": 1.0
      },
      {
        "x": 7,
        "y": 0,
        "type": "TechSlotPropertyModifier",
        "property": "MaxHealth",
        "calculatedValue": 33.44,
        "value": 33.0
      },
      {
        "x": 8,
        "y": 0,
        "type": "TechSlotPropertyModifier",
        "property": "Damage",
        "calculatedValue": 0.8818258,
        "value": 1.0
      },
      {
        "x": 9,
        "y": 0,
        "type": "TechSlotPropertyModifier",
        "property": "MaxHealth",
        "calculatedValue": 40.6057129,
        "value": 41.0
      },
      {
        "x": 10,
        "y": 0,
        "type": "TechSlotPropertyModifier",
        "property": "Damage",
        "calculatedValue": 1.0735271,
        "value": 1.0
      },
      {
        "x": 11,
        "y": 0,
        "type": "TechSlotPropertyModifier",
        "property": "MaxHealth",
        "calculatedValue": 48.56762,
        "value": 49.0
      },
      {
        "x": 12,
        "y": 0,
        "type": "TechSlotPowerValueModifier",
        "property": "PowerRangeAbs",
        "calculatedValue": 0.125,
        "value": 0.12
      },
      {
        "x": 13,
        "y": 0,
        "type": "TechSlotPropertyModifier",
        "property": "Damage",
        "calculatedValue": 1.34190881,
        "value": 1.0
      },
      {
        "x": 14,
        "y": 0,
        "type": "TechSlotPropertyModifier",
        "property": "MaxHealth",
        "calculatedValue": 19.35635,
        "value": 19.0
      },
      {
        "x": 15,
        "y": 0,
        "type": "TechSlotPropertyModifier",
        "property": "Damage",
        "calculatedValue": 0.829230845,
        "value": 1.0
      },
      {
        "x": 16,
        "y": 0,
        "type": "TechSlotPropertyModifier",
        "property": "MaxHealth",
        "calculatedValue": 23.7271366,
        "value": 24.0
      },
      {
        "x": 17,
        "y": 0,
        "type": "TechSlotPropertyModifier",
        "property": "Damage",
        "calculatedValue": 0.995077,
        "value": 1.0
      },
      {
        "x": 18,
        "y": 0,
        "type": "TechSlotPropertyModifier",
        "property": "MaxHealth",
        "calculatedValue": 28.7223263,
        "value": 29.0
      },
      {
        "x": 19,
        "y": 0,
        "type": "TechSlotPropertyModifier",
        "property": "Damage",
        "calculatedValue": 1.20830786,
        "value": 1.0
      },
      {
        "x": 20,
        "y": 0,
        "type": "TechSlotPropertyModifier",
        "property": "MaxHealth",
        "calculatedValue": 34.96631,
        "value": 35.0
      },
      {
        "x": 21,
        "y": 0,
        "type": "TechSlotPowerValueModifier",
        "property": "PowerRangeAbs",
        "calculatedValue": 0.125,
        "value": 0.12
      },
      {
        "x": 22,
        "y": 0,
        "type": "TechSlotPropertyModifier",
        "property": "Damage",
        "calculatedValue": 1.58738482,
        "value": 2.0
      },
      {
        "x": 23,
        "y": 0,
        "type": "TechSlotPropertyModifier",
        "property": "MaxHealth",
        "calculatedValue": 43.7078857,
        "value": 44.0
      },
      {
        "x": 24,
        "y": 0,
        "type": "TechSlotPropertyModifier",
        "property": "Damage",
        "calculatedValue": 0.482764065,
        "value": 1.0
      },
      {
        "x": 25,
        "y": 0,
        "type": "TechSlotPropertyModifier",
        "property": "MaxHealth",
        "calculatedValue": 15.9923086,
        "value": 16.0
      },
      {
        "x": 26,
        "y": 0,
        "type": "TechSlotPropertyModifier",
        "property": "Damage",
        "calculatedValue": 0.5917753,
        "value": 1.0
      },
      {
        "x": 27,
        "y": 0,
        "type": "TechSlotPropertyModifier",
        "property": "MaxHealth",
        "calculatedValue": 19.19077,
        "value": 19.0
      },
      {
        "x": 28,
        "y": 0,
        "type": "TechSlotPropertyModifier",
        "property": "Damage",
        "calculatedValue": 0.716359556,
        "value": 1.0
      },
      {
        "x": 29,
        "y": 0,
        "type": "TechSlotPropertyModifier",
        "property": "MaxHealth",
        "calculatedValue": 23.3030777,
        "value": 23.0
      },
      {
        "x": 30,
        "y": 0,
        "type": "TechSlotPowerValueModifier",
        "property": "PowerRangeAbs",
        "calculatedValue": 0.125,
        "value": 0.12
      },
      {
        "x": 31,
        "y": 0,
        "type": "TechSlotPropertyModifier",
        "property": "Damage",
        "calculatedValue": 0.9499551,
        "value": 1.0
      },
      {
        "x": 32,
        "y": 0,
        "type": "TechSlotPropertyModifier",
        "property": "MaxHealth",
        "calculatedValue": 30.6138477,
        "value": 31.0
      },
      {
        "x": 33,
        "y": 0,
        "type": "TechSlotPropertyModifier",
        "property": "Damage",
        "calculatedValue": 1.09011245,
        "value": 1.0
      },
      {
        "x": 34,
        "y": 0,
        "type": "TechSlotPropertyModifier",
        "property": "MaxHealth",
        "calculatedValue": 36.55385,
        "value": 37.0
      },
      {
        "x": 35,
        "y": 0,
        "type": "TechSlotPropertyModifier",
        "property": "Damage",
        "calculatedValue": 1.40157318,
        "value": 1.0
      },
      {
        "x": 36,
        "y": 0,
        "type": "TechSlotPropertyModifier",
        "property": "MaxHealth",
        "calculatedValue": 45.2353859,
        "value": 45.0
      },
      {
        "x": 37,
        "y": 0,
        "type": "TechSlotPropertyModifier",
        "property": "Damage",
        "calculatedValue": 1.69746065,
        "value": 2.0
      },
      {
        "x": 38,
        "y": 0,
        "type": "TechSlotPropertyModifier",
        "property": "MaxHealth",
        "calculatedValue": 54.83077,
        "value": 55.0
      },
      {
        "x": 39,
        "y": 0,
        "type": "TechSlotPowerValueModifier",
        "property": "PowerRangeAbs",
        "calculatedValue": 0.125,
        "value": 0.12
      },
      {
        "x": 40,
        "y": 0,
        "type": "TechSlotPropertyModifier",
        "property": "Damage",
        "calculatedValue": 0.231946722,
        "value": 1.0
      },
      {
        "x": 41,
        "y": 0,
        "type": "TechSlotPropertyModifier",
        "property": "MaxHealth",
        "calculatedValue": 9.85903549,
        "value": 10.0
      },
      {
        "x": 42,
        "y": 0,
        "type": "TechSlotPropertyModifier",
        "property": "Damage",
        "calculatedValue": 0.278336048,
        "value": 1.0
      },
      {
        "x": 43,
        "y": 0,
        "type": "TechSlotPropertyModifier",
        "property": "MaxHealth",
        "calculatedValue": 11.9346218,
        "value": 12.0
      },
      {
        "x": 44,
        "y": 0,
        "type": "TechSlotPropertyModifier",
        "property": "Damage",
        "calculatedValue": 0.3379795,
        "value": 1.0
      },
      {
        "x": 45,
        "y": 0,
        "type": "TechSlotPropertyModifier",
        "property": "MaxHealth",
        "calculatedValue": 14.5291052,
        "value": 15.0
      },
      {
        "x": 46,
        "y": 0,
        "type": "TechSlotPropertyModifier",
        "property": "Damage",
        "calculatedValue": 0.40425,
        "value": 1.0
      },
      {
        "x": 47,
        "y": 0,
        "type": "TechSlotPropertyModifier",
        "property": "MaxHealth",
        "calculatedValue": 17.3830376,
        "value": 17.0
      },
      {
        "x": 48,
        "y": 0,
        "type": "TechSlotPowerValueModifier",
        "property": "PowerRangeAbs",
        "calculatedValue": 0.125,
        "value": 0.12
      },
      {
        "x": 49,
        "y": 0,
        "type": "TechSlotPropertyModifier",
        "property": "Damage",
        "calculatedValue": 0.5301639,
        "value": 1.0
      },
      {
        "x": 50,
        "y": 0,
        "type": "TechSlotPropertyModifier",
        "property": "MaxHealth",
        "calculatedValue": 23.3503475,
        "value": 23.0
      },
      {
        "x": 51,
        "y": 0,
        "type": "TechSlotPropertyModifier",
        "property": "Damage",
        "calculatedValue": 0.656077862,
        "value": 1.0
      },
      {
        "x": 52,
        "y": 0,
        "type": "TechSlotPropertyModifier",
        "property": "MaxHealth",
        "calculatedValue": 28.2798653,
        "value": 28.0
      },
      {
        "x": 53,
        "y": 0,
        "type": "TechSlotPropertyModifier",
        "property": "Damage",
        "calculatedValue": 0.7952459,
        "value": 1.0
      },
      {
        "x": 54,
        "y": 0,
        "type": "TechSlotPropertyModifier",
        "property": "MaxHealth",
        "calculatedValue": 5.059523,
        "value": 5.0
      },
      {
        "x": 55,
        "y": 0,
        "type": "TechSlotPropertyModifier",
        "property": "Damage",
        "calculatedValue": 0.205725208,
        "value": 1.0
      },
      {
        "x": 56,
        "y": 0,
        "type": "TechSlotPropertyModifier",
        "property": "MaxHealth",
        "calculatedValue": 6.201996,
        "value": 6.0
      },
      {
        "x": 57,
        "y": 0,
        "type": "TechSlotPowerValueModifier",
        "property": "PowerRangeAbs",
        "calculatedValue": 0.125,
        "value": 0.12
      },
      {
        "x": 58,
        "y": 0,
        "type": "TechSlotPropertyModifier",
        "property": "Damage",
        "calculatedValue": 0.2703817,
        "value": 1.0
      },
      {
        "x": 59,
        "y": 0,
        "type": "TechSlotPropertyModifier",
        "property": "MaxHealth",
        "calculatedValue": 8.323731,
        "value": 8.0
      },
      {
        "x": 60,
        "y": 0,
        "type": "TechSlotPropertyModifier",
        "property": "Damage",
        "calculatedValue": 0.329160333,
        "value": 1.0
      },
      {
        "x": 61,
        "y": 0,
        "type": "TechSlotPropertyModifier",
        "property": "MaxHealth",
        "calculatedValue": 9.955835,
        "value": 10.0
      },
      {
        "x": 62,
        "y": 0,
        "type": "TechSlotPropertyModifier",
        "property": "Damage",
        "calculatedValue": 0.393816829,
        "value": 1.0
      },
      {
        "x": 63,
        "y": 0,
        "type": "TechSlotPropertyModifier",
        "property": "MaxHealth",
        "calculatedValue": 11.4247293,
        "value": 11.0
      },
      {
        "x": 64,
        "y": 0,
        "type": "TechSlotPropertyModifier",
        "property": "Damage",
        "calculatedValue": 0.47022903,
        "value": 1.0
      },
      {
        "x": 65,
        "y": 0,
        "type": "TechSlotPropertyModifier",
        "property": "MaxHealth",
        "calculatedValue": 14.6889381,
        "value": 15.0
      },
      {
        "x": 66,
        "y": 0,
        "type": "TechSlotPowerValueModifier",
        "property": "PowerRangeAbs",
        "calculatedValue": 0.125,
        "value": 0.12
      },
      {
        "x": 67,
        "y": 0,
        "type": "TechSlotPropertyModifier",
        "property": "Damage",
        "calculatedValue": 0.640687048,
        "value": 1.0
      },
      {
        "x": 68,
        "y": 0,
        "type": "TechSlotPropertyModifier",
        "property": "MaxHealth",
        "calculatedValue": 19.5852489,
        "value": 20.0
      }
    ],
    "Evolve": [
      {
        "StarLevel": 0,
        "Slots": [
          {
            "x": 0,
            "y": 0,
            "type": "TechSlotPropertyModifier",
            "property": "MaxHealth",
            "calculatedValue": 125.400009,
            "value": 125.0
          },
          {
            "x": 0,
            "y": 0,
            "type": "TechSlotPropertyModifier",
            "property": "Damage",
            "calculatedValue": 3.85000014,
            "value": 4.0
          }
        ]
      },
      {
        "StarLevel": 1,
        "Slots": [
          {
            "x": 0,
            "y": 0,
            "type": "TechSlotPropertyModifier",
            "property": "MaxHealth",
            "calculatedValue": 376.200043,
            "value": 376.0
          },
          {
            "x": 0,
            "y": 0,
            "type": "TechSlotPropertyModifier",
            "property": "Damage",
            "calculatedValue": 11.55,
            "value": 12.0
          }
        ]
      },
      {
        "StarLevel": 2,
        "Slots": [
          {
            "x": 0,
            "y": 0,
            "type": "TechSlotPropertyModifier",
            "property": "MaxHealth",
            "calculatedValue": 250.800018,
            "value": 251.0
          },
          {
            "x": 0,
            "y": 0,
            "type": "TechSlotPropertyModifier",
            "property": "Damage",
            "calculatedValue": 7.70000029,
            "value": 8.0
          }
        ]
      },
      {
        "StarLevel": 3,
        "Slots": [
          {
            "x": 0,
            "y": 0,
            "type": "TechSlotPropertyModifier",
            "property": "MaxHealth",
            "calculatedValue": 125.400009,
            "value": 125.0
          },
          {
            "x": 0,
            "y": 0,
            "type": "TechSlotPropertyModifier",
            "property": "Damage",
            "calculatedValue": 3.85000014,
            "value": 4.0
          }
        ]
      },
      {
        "StarLevel": 4,
        "Slots": [
          {
            "x": 0,
            "y": 0,
            "type": "TechSlotPropertyModifier",
            "property": "MaxHealth",
            "calculatedValue": 125.400009,
            "value": 125.0
          },
          {
            "x": 0,
            "y": 0,
            "type": "TechSlotPropertyModifier",
            "property": "Damage",
            "calculatedValue": 3.85000014,
            "value": 4.0
          }
        ]
      },
      {
        "StarLevel": 5,
        "Slots": [
          {
            "x": 0,
            "y": 0,
            "type": "TechSlotPropertyModifier",
            "property": "MaxHealth",
            "calculatedValue": 125.400009,
            "value": 125.0
          },
          {
            "x": 0,
            "y": 0,
            "type": "TechSlotPropertyModifier",
            "property": "Damage",
            "calculatedValue": 3.85000014,
            "value": 4.0
          }
        ]
      }
    ]
  },
  "Requirements": {
    "MinEpisodeCompleted": 3,
    "MinPlayerLevel": 0,
    "MinPVPRank": 5,
    "MinPVPArena": 2
  },
  "AOEAttackType": "No",
  "AOEDamagePercentage": 0.0,
  "AOERadius": 0.0,
  "AOEKnockbackPercentage": 0.0,
  "TargetingType": "Ground",
  "PreAttackDelay": 0.0,
  "CanCastOnLava": false,
  "CastArea": "OwnSide",
  "TechtreePatterns": {
    "Upgrades": [
      {
        "PatternType": 0,
        "SlotType": "TechSlotPowerValueModifier",
        "SlotProperty": "PowerRangeAbs",
        "SlotValue": "",
        "MaxMultiplier": "1.5",
        "PowerValue": "2",
        "StartIndex": 4,
        "EndIndex": 0,
        "RepeatInterval": 9,
        "Weighted": false
      }
    ],
    "Evolutions": []
  },
  "OverrideSoundBankName": "",
  "ChildUnitLimit": 0,
  "SpineSkin": "",
  "CastOverrideAnim": "",
  "ColliderRadiusOverride": -1.0,
  "AttackEffect": "",
  "CheckAndRemoveFromDeckOnSpawn": false
}