{
  "Id": 1650,
  "Visible": false,
  "Finalized": true,
  "UnlockedDuringEvent": false,
  "CanAttack": true,
  "NameKey": "[PVE] Special SCI Melee Kid",
  "OasisNameOverride": "",
  "OasisDescOverride": "",
  "Image": "KidspecialmeleeSciCard",
  "Frame": "",
  "ManaCost": 3,
  "Damage": "25",
  "Health": "70",
  "HealthLoss": "0",
  "Type": "Character",
  "IngameAssets": [
    "CyborgkidspecialmeleeSciCharPF",
    "ChargedPowerRet",
    "TargetSpellRet"
  ],
  "UIAssets": [
    "KidspecialmeleeSciCard"
  ],
  "Targeting": {
    "AssetId": "TargetSpellRet",
    "Radius": 0.0
  },
  "CardUI": "CharCardUI",
  "Tags": [
    "Character",
    "Common",
    "Enemy",
    "Human",
    "Kids",
    "Male",
    "Melee",
    "Sci"
  ],
  "CharacterType": "Melee",
  "Ingame": "CyborgkidspecialmeleeSciCharPF",
  "AttackRange": 0.4,
  "TimeToReachMaxVelocity": 0.1,
  "MaxVelocity": 0.675,
  "TimeInBetweenAttacks": 0.5,
  "AgroRangeMultiplier": 7.5,
  "_notes": "",
  "PhysicsProperties": {
    "FrictionCoefficient": 1.0,
    "RestingFriction": 0.25,
    "BounceFactor": 0.9,
    "Weight": 35.0
  },
  "KnockbackImpulse": "25.0000",
  "KnockbackAngleDeg": 45.0,
  "ChargedPowerRegen": 0.06666667,
  "ChargedPowerRadius": 0.0,
  "ChargedPowerReticle": "ChargedPowerRet",
  "Rarity": 0,
  "Theme": "Sci",
  "RetreatDistanceFactor": 0.8,
  "RetreatVelocityFactor": 0.3,
  "WalkingAnimationThresholdFactor": 0.2,
  "TargetHeightFactor": 0.8,
  "HealthBarOffset": -0.35,
  "Pows": [
    {
      "Trigger": {
        "Type": "ChargedPowerActivated",
        "Params": {
          "Automatic": false,
          "EnabledByTechTree": false,
          "EnabledByFSM": false
        }
      },
      "UniqueId": "1650_Special Enemy Malee Kid_0",
      "Nodes": [
        {
          "Type": "AllUnitsSelector"
        },
        {
          "Type": "FilterFriendsSelector"
        },
        {
          "Type": "FilterByTagSelector",
          "Params": {
            "IncludeAll": false,
            "CanSelectAnyUnits": false,
            "ExcludeTags": "MovingObject,Object,SpeedchangeImmune"
          }
        },
        {
          "Type": "SpeedUpEffect",
          "EffectImpact": "Neutral",
          "Params": {
            "SpeedMultiplier": "2",
            "AffectsAnimations": true,
            "HideIcon": true
          },
          "EndTriggers": [
            {
              "Type": "ElapsedTimeSinceActivation",
              "Params": {
                "ElapsedTime": "3",
                "ElapsedTimeVariableId": "PowerDuration"
              }
            }
          ]
        },
        {
          "Type": "FocusEffect",
          "Params": {
            "OnStart": true
          }
        },
        {
          "Type": "VisualEffect",
          "EffectImpact": "Neutral",
          "Params": {
            "AssetId": "SpeedUpOncePowerFX",
            "BoneName": "Target",
            "OwnerTeamOnly": false
          }
        },
        {
          "Type": "VisualEffect",
          "EffectImpact": "Neutral",
          "Params": {
            "AssetId": "SpeedUpTargetLoopPowerFX",
            "BoneName": "Target",
            "OwnerTeamOnly": false
          },
          "EndTriggers": [
            {
              "Type": "ElapsedTimeSinceActivation",
              "Params": {
                "ElapsedTime": "3"
              }
            }
          ]
        },
        {
          "Type": "FilterByTagSelector",
          "Params": {
            "IncludeAll": false,
            "CanSelectAnyUnits": false,
            "ExcludeTags": "Flying"
          }
        },
        {
          "Type": "VisualEffect",
          "EffectImpact": "Neutral",
          "Params": {
            "AssetId": "SpeedUpGroundTargetLoopPowerFX",
            "OwnerTeamOnly": false
          },
          "EndTriggers": [
            {
              "Type": "ElapsedTimeSinceActivation",
              "Params": {
                "ElapsedTime": "3"
              }
            }
          ]
        }
      ]
    }
  ],
  "SameTeamCollisionRadiusMultiplier": 1.0,
  "TechTree2": {
    "Slots": [
      {
        "x": 0,
        "y": 0,
        "type": "TechSlotPropertyModifier",
        "property": "MaxHealth",
        "calculatedValue": 2.868174,
        "value": 3.0
      },
      {
        "x": 1,
        "y": 0,
        "type": "TechSlotPropertyModifier",
        "property": "Damage",
        "calculatedValue": 1.03636372,
        "value": 1.0
      },
      {
        "x": 2,
        "y": 0,
        "type": "TechSlotPropertyModifier",
        "property": "MaxHealth",
        "calculatedValue": 3.51582623,
        "value": 4.0
      },
      {
        "x": 3,
        "y": 0,
        "type": "TechSlotPropertyModifier",
        "property": "Damage",
        "calculatedValue": 1.24363649,
        "value": 1.0
      },
      {
        "x": 4,
        "y": 0,
        "type": "TechSlotPropertyModifier",
        "property": "MaxHealth",
        "calculatedValue": 1.94023526,
        "value": 2.0
      },
      {
        "x": 5,
        "y": 0,
        "type": "TechSlotPropertyModifier",
        "property": "Damage",
        "calculatedValue": 0.718919,
        "value": 1.0
      },
      {
        "x": 6,
        "y": 0,
        "type": "TechSlotPropertyModifier",
        "property": "MaxHealth",
        "calculatedValue": 2.37835288,
        "value": 2.0
      },
      {
        "x": 7,
        "y": 0,
        "type": "TechSlotPropertyModifier",
        "property": "Damage",
        "calculatedValue": 0.8627028,
        "value": 1.0
      },
      {
        "x": 8,
        "y": 0,
        "type": "TechSlotPropertyModifier",
        "property": "MaxHealth",
        "calculatedValue": 2.87905884,
        "value": 3.0
      },
      {
        "x": 9,
        "y": 0,
        "type": "TechSlotPropertyModifier",
        "property": "Damage",
        "calculatedValue": 1.04756761,
        "value": 1.0
      },
      {
        "x": 10,
        "y": 0,
        "type": "TechSlotPropertyModifier",
        "property": "MaxHealth",
        "calculatedValue": 3.50494123,
        "value": 4.0
      },
      {
        "x": 11,
        "y": 0,
        "type": "TechSlotPropertyModifier",
        "property": "Damage",
        "calculatedValue": 1.25297308,
        "value": 1.0
      },
      {
        "x": 12,
        "y": 0,
        "type": "TechSlotPropertyModifier",
        "property": "MaxHealth",
        "calculatedValue": 4.193412,
        "value": 4.0
      },
      {
        "x": 13,
        "y": 0,
        "type": "TechSlotPropertyModifier",
        "property": "Damage",
        "calculatedValue": 1.437838,
        "value": 1.0
      },
      {
        "x": 14,
        "y": 0,
        "type": "TechSlotPropertyModifier",
        "property": "MaxHealth",
        "calculatedValue": 1.94023526,
        "value": 2.0
      },
      {
        "x": 15,
        "y": 0,
        "type": "TechSlotPropertyModifier",
        "property": "Damage",
        "calculatedValue": 0.718919,
        "value": 1.0
      },
      {
        "x": 16,
        "y": 0,
        "type": "TechSlotPropertyModifier",
        "property": "MaxHealth",
        "calculatedValue": 2.37835288,
        "value": 2.0
      },
      {
        "x": 17,
        "y": 0,
        "type": "TechSlotPropertyModifier",
        "property": "Damage",
        "calculatedValue": 0.8627028,
        "value": 1.0
      },
      {
        "x": 18,
        "y": 0,
        "type": "TechSlotPropertyModifier",
        "property": "MaxHealth",
        "calculatedValue": 2.87905884,
        "value": 3.0
      },
      {
        "x": 19,
        "y": 0,
        "type": "TechSlotPropertyModifier",
        "property": "Damage",
        "calculatedValue": 1.04756761,
        "value": 1.0
      },
      {
        "x": 20,
        "y": 0,
        "type": "TechSlotPropertyModifier",
        "property": "MaxHealth",
        "calculatedValue": 3.50494123,
        "value": 4.0
      },
      {
        "x": 21,
        "y": 0,
        "type": "TechSlotPropertyModifier",
        "property": "Damage",
        "calculatedValue": 1.25297308,
        "value": 1.0
      },
      {
        "x": 22,
        "y": 0,
        "type": "TechSlotPropertyModifier",
        "property": "MaxHealth",
        "calculatedValue": 4.193412,
        "value": 4.0
      },
      {
        "x": 23,
        "y": 0,
        "type": "TechSlotPropertyModifier",
        "property": "Damage",
        "calculatedValue": 1.437838,
        "value": 1.0
      },
      {
        "x": 24,
        "y": 0,
        "type": "TechSlotPropertyModifier",
        "property": "MaxHealth",
        "calculatedValue": 1.35129976,
        "value": 1.0
      },
      {
        "x": 25,
        "y": 0,
        "type": "TechSlotPropertyModifier",
        "property": "Damage",
        "calculatedValue": 0.6388647,
        "value": 1.0
      },
      {
        "x": 26,
        "y": 0,
        "type": "TechSlotPropertyModifier",
        "property": "MaxHealth",
        "calculatedValue": 1.656432,
        "value": 2.0
      },
      {
        "x": 27,
        "y": 0,
        "type": "TechSlotPropertyModifier",
        "property": "Damage",
        "calculatedValue": 0.7666376,
        "value": 1.0
      },
      {
        "x": 28,
        "y": 0,
        "type": "TechSlotPropertyModifier",
        "property": "MaxHealth",
        "calculatedValue": 2.00515461,
        "value": 2.0
      },
      {
        "x": 29,
        "y": 0,
        "type": "TechSlotPropertyModifier",
        "property": "Damage",
        "calculatedValue": 0.9309171,
        "value": 1.0
      },
      {
        "x": 30,
        "y": 0,
        "type": "TechSlotPropertyModifier",
        "property": "MaxHealth",
        "calculatedValue": 2.441058,
        "value": 2.0
      },
      {
        "x": 31,
        "y": 0,
        "type": "TechSlotPropertyModifier",
        "property": "Damage",
        "calculatedValue": 1.11344993,
        "value": 1.0
      },
      {
        "x": 32,
        "y": 0,
        "type": "TechSlotPropertyModifier",
        "property": "MaxHealth",
        "calculatedValue": 2.9205513,
        "value": 3.0
      },
      {
        "x": 33,
        "y": 0,
        "type": "TechSlotPropertyModifier",
        "property": "Damage",
        "calculatedValue": 1.27772939,
        "value": 1.0
      },
      {
        "x": 34,
        "y": 0,
        "type": "TechSlotPropertyModifier",
        "property": "MaxHealth",
        "calculatedValue": 3.48722529,
        "value": 3.0
      },
      {
        "x": 35,
        "y": 0,
        "type": "TechSlotPropertyModifier",
        "property": "Damage",
        "calculatedValue": 1.642795,
        "value": 2.0
      },
      {
        "x": 36,
        "y": 0,
        "type": "TechSlotPropertyModifier",
        "property": "MaxHealth",
        "calculatedValue": 4.315441,
        "value": 4.0
      },
      {
        "x": 37,
        "y": 0,
        "type": "TechSlotPropertyModifier",
        "property": "Damage",
        "calculatedValue": 1.9896071,
        "value": 2.0
      },
      {
        "x": 38,
        "y": 0,
        "type": "TechSlotPropertyModifier",
        "property": "MaxHealth",
        "calculatedValue": 5.230838,
        "value": 5.0
      },
      {
        "x": 39,
        "y": 0,
        "type": "TechSlotPropertyModifier",
        "property": "Damage",
        "calculatedValue": 0.482607126,
        "value": 1.0
      },
      {
        "x": 40,
        "y": 0,
        "type": "TechSlotPropertyModifier",
        "property": "MaxHealth",
        "calculatedValue": 1.788821,
        "value": 2.0
      },
      {
        "x": 41,
        "y": 0,
        "type": "TechSlotPropertyModifier",
        "property": "Damage",
        "calculatedValue": 0.5915829,
        "value": 1.0
      },
      {
        "x": 42,
        "y": 0,
        "type": "TechSlotPropertyModifier",
        "property": "MaxHealth",
        "calculatedValue": 2.146585,
        "value": 2.0
      },
      {
        "x": 43,
        "y": 0,
        "type": "TechSlotPropertyModifier",
        "property": "Damage",
        "calculatedValue": 0.71612674,
        "value": 1.0
      },
      {
        "x": 44,
        "y": 0,
        "type": "TechSlotPropertyModifier",
        "property": "MaxHealth",
        "calculatedValue": 2.60656762,
        "value": 3.0
      },
      {
        "x": 45,
        "y": 0,
        "type": "TechSlotPropertyModifier",
        "property": "Damage",
        "calculatedValue": 0.871806443,
        "value": 1.0
      },
      {
        "x": 46,
        "y": 0,
        "type": "TechSlotPropertyModifier",
        "property": "MaxHealth",
        "calculatedValue": 3.11765933,
        "value": 3.0
      },
      {
        "x": 47,
        "y": 0,
        "type": "TechSlotPropertyModifier",
        "property": "Damage",
        "calculatedValue": 1.0430541,
        "value": 1.0
      },
      {
        "x": 48,
        "y": 0,
        "type": "TechSlotPropertyModifier",
        "property": "MaxHealth",
        "calculatedValue": 3.577642,
        "value": 4.0
      },
      {
        "x": 49,
        "y": 0,
        "type": "TechSlotPropertyModifier",
        "property": "Damage",
        "calculatedValue": 1.24543774,
        "value": 1.0
      },
      {
        "x": 50,
        "y": 0,
        "type": "TechSlotPropertyModifier",
        "property": "MaxHealth",
        "calculatedValue": 4.59982538,
        "value": 5.0
      },
      {
        "x": 51,
        "y": 0,
        "type": "TechSlotPropertyModifier",
        "property": "Damage",
        "calculatedValue": 1.54122925,
        "value": 2.0
      },
      {
        "x": 52,
        "y": 0,
        "type": "TechSlotPropertyModifier",
        "property": "MaxHealth",
        "calculatedValue": 5.57089949,
        "value": 6.0
      },
      {
        "x": 53,
        "y": 0,
        "type": "TechSlotPropertyModifier",
        "property": "Damage",
        "calculatedValue": 1.86815667,
        "value": 2.0
      },
      {
        "x": 54,
        "y": 0,
        "type": "TechSlotPropertyModifier",
        "property": "MaxHealth",
        "calculatedValue": 1.35129976,
        "value": 1.0
      },
      {
        "x": 55,
        "y": 0,
        "type": "TechSlotPropertyModifier",
        "property": "Damage",
        "calculatedValue": 0.6388647,
        "value": 1.0
      },
      {
        "x": 56,
        "y": 0,
        "type": "TechSlotPropertyModifier",
        "property": "MaxHealth",
        "calculatedValue": 1.656432,
        "value": 2.0
      },
      {
        "x": 57,
        "y": 0,
        "type": "TechSlotPropertyModifier",
        "property": "Damage",
        "calculatedValue": 0.7666376,
        "value": 1.0
      },
      {
        "x": 58,
        "y": 0,
        "type": "TechSlotPropertyModifier",
        "property": "MaxHealth",
        "calculatedValue": 2.00515461,
        "value": 2.0
      },
      {
        "x": 59,
        "y": 0,
        "type": "TechSlotPropertyModifier",
        "property": "Damage",
        "calculatedValue": 0.9309171,
        "value": 1.0
      },
      {
        "x": 60,
        "y": 0,
        "type": "TechSlotPropertyModifier",
        "property": "MaxHealth",
        "calculatedValue": 2.441058,
        "value": 2.0
      },
      {
        "x": 61,
        "y": 0,
        "type": "TechSlotPropertyModifier",
        "property": "Damage",
        "calculatedValue": 1.11344993,
        "value": 1.0
      },
      {
        "x": 62,
        "y": 0,
        "type": "TechSlotPropertyModifier",
        "property": "MaxHealth",
        "calculatedValue": 2.9205513,
        "value": 3.0
      },
      {
        "x": 63,
        "y": 0,
        "type": "TechSlotPropertyModifier",
        "property": "Damage",
        "calculatedValue": 1.27772939,
        "value": 1.0
      },
      {
        "x": 64,
        "y": 0,
        "type": "TechSlotPropertyModifier",
        "property": "MaxHealth",
        "calculatedValue": 3.48722529,
        "value": 3.0
      },
      {
        "x": 65,
        "y": 0,
        "type": "TechSlotPropertyModifier",
        "property": "Damage",
        "calculatedValue": 1.642795,
        "value": 2.0
      },
      {
        "x": 66,
        "y": 0,
        "type": "TechSlotPropertyModifier",
        "property": "MaxHealth",
        "calculatedValue": 4.315441,
        "value": 4.0
      },
      {
        "x": 67,
        "y": 0,
        "type": "TechSlotPropertyModifier",
        "property": "Damage",
        "calculatedValue": 1.9896071,
        "value": 2.0
      },
      {
        "x": 68,
        "y": 0,
        "type": "TechSlotPropertyModifier",
        "property": "MaxHealth",
        "calculatedValue": 5.230838,
        "value": 5.0
      }
    ],
    "Evolve": [
      {
        "StarLevel": 0,
        "Slots": [
          {
            "x": 0,
            "y": 0,
            "type": "TechSlotPropertyModifier",
            "property": "MaxHealth",
            "calculatedValue": 9.975,
            "value": 10.0
          },
          {
            "x": 0,
            "y": 0,
            "type": "TechSlotPropertyModifier",
            "property": "Damage",
            "calculatedValue": 3.56250048,
            "value": 4.0
          }
        ]
      },
      {
        "StarLevel": 1,
        "Slots": [
          {
            "x": 0,
            "y": 0,
            "type": "TechSlotPropertyModifier",
            "property": "MaxHealth",
            "calculatedValue": 14.9625006,
            "value": 15.0
          },
          {
            "x": 0,
            "y": 0,
            "type": "TechSlotPropertyModifier",
            "property": "Damage",
            "calculatedValue": 5.343751,
            "value": 5.0
          }
        ]
      },
      {
        "StarLevel": 2,
        "Slots": [
          {
            "x": 0,
            "y": 0,
            "type": "TechSlotPropertyModifier",
            "property": "MaxHealth",
            "calculatedValue": 19.95,
            "value": 20.0
          },
          {
            "x": 0,
            "y": 0,
            "type": "TechSlotPropertyModifier",
            "property": "Damage",
            "calculatedValue": 7.125001,
            "value": 7.0
          }
        ]
      },
      {
        "StarLevel": 3,
        "Slots": [
          {
            "x": 0,
            "y": 0,
            "type": "TechSlotPropertyModifier",
            "property": "MaxHealth",
            "calculatedValue": 24.9375,
            "value": 25.0
          },
          {
            "x": 0,
            "y": 0,
            "type": "TechSlotPropertyModifier",
            "property": "Damage",
            "calculatedValue": 8.906251,
            "value": 9.0
          }
        ]
      },
      {
        "StarLevel": 4,
        "Slots": [
          {
            "x": 0,
            "y": 0,
            "type": "TechSlotPropertyModifier",
            "property": "MaxHealth",
            "calculatedValue": 39.9,
            "value": 40.0
          },
          {
            "x": 0,
            "y": 0,
            "type": "TechSlotPropertyModifier",
            "property": "Damage",
            "calculatedValue": 14.2500019,
            "value": 14.0
          }
        ]
      },
      {
        "StarLevel": 5,
        "Slots": [
          {
            "x": 0,
            "y": 0,
            "type": "TechSlotPropertyModifier",
            "property": "MaxHealth",
            "calculatedValue": 49.875,
            "value": 50.0
          },
          {
            "x": 0,
            "y": 0,
            "type": "TechSlotPropertyModifier",
            "property": "Damage",
            "calculatedValue": 17.8125019,
            "value": 18.0
          }
        ]
      }
    ]
  },
  "Requirements": {
    "MinEpisodeCompleted": 0,
    "MinPlayerLevel": 0,
    "MinPVPRank": 0,
    "MinPVPArena": 0
  },
  "AOEAttackType": "No",
  "AOEDamagePercentage": 0.0,
  "AOERadius": 0.0,
  "AOEKnockbackPercentage": 0.0,
  "TargetingType": "Ground",
  "PreAttackDelay": 0.0,
  "CanCastOnLava": false,
  "CastArea": "OwnSide",
  "TechtreePatterns": {
    "Upgrades": [],
    "Evolutions": []
  },
  "OverrideSoundBankName": "CyborgkidmeleeSci",
  "ChildUnitLimit": 0,
  "SpineSkin": "",
  "ColliderRadiusOverride": -1.0,
  "CheckAndRemoveFromDeckOnSpawn": false
}